jumonc_nekrs/jumonc_nekrs_plugin.py
jumonc_nekrs/nekrs_status_schema.json
jumonc_nekrs-0.3.1rc2.dist-info/LICENSE
jumonc_nekrs-0.3.1rc2.dist-info/METADATA
jumonc_nekrs-0.3.1rc2.dist-info/WHEEL
jumonc_nekrs-0.3.1rc2.dist-info/entry_points.txt
jumonc_nekrs-0.3.1rc2.dist-info/top_level.txt
jumonc_nekrs-0.3.1rc2.dist-info/RECORD
