Metadata-Version: 2.1
Name: jumonc-nekrs
Version: 0.3.1rc2
Summary: LogParser jumonc plugin for nekRS
Home-page: https://gitlab.jsc.fz-juelich.de/coec/jumonc_nekrs
Author: Christian Witzler
Author-email: c.witzler@fz-juelich.de
License: BSD 3-Clause License
Platform: UNKNOWN
Classifier: License :: OSI Approved :: BSD License
Classifier: Programming Language :: Python :: 3
Classifier: Programming Language :: Python :: 3.9
License-File: LICENSE
Requires-Dist: JuMonC (>=0.10.0rc3)
Requires-Dist: pluggy
